chromosight/__init__.py
chromosight/version.py
chromosight/cli/__init__.py
chromosight/cli/chromosight.py
chromosight/cli/logo.txt
chromosight/kernels/__init__.py
chromosight/kernels/artificial_template_borders_type1.txt
chromosight/kernels/artificial_template_borders_type2.txt
chromosight/kernels/artificial_template_borders_type3.txt
chromosight/kernels/artificial_template_hairpin.txt
chromosight/kernels/artificial_template_loops_small.txt
chromosight/kernels/artificial_template_loops_type1.txt
chromosight/kernels/borders.json
chromosight/kernels/centromeres.1.txt
chromosight/kernels/centromeres.json
chromosight/kernels/hairpins.json
chromosight/kernels/loops.json
chromosight/kernels/loops_small.json
chromosight/kernels/stripes_left.1.txt
chromosight/kernels/stripes_left.json
chromosight/kernels/stripes_right.1.txt
chromosight/kernels/stripes_right.json
chromosight/utils/__init__.py
chromosight/utils/contacts_map.py
chromosight/utils/detection.py
chromosight/utils/io.py
chromosight/utils/plotting.py
chromosight/utils/preprocessing.py
chromosight/utils/stats.py
chromosight-1.6.3.dist-info/LICENSE
chromosight-1.6.3.dist-info/METADATA
chromosight-1.6.3.dist-info/WHEEL
chromosight-1.6.3.dist-info/entry_points.txt
chromosight-1.6.3.dist-info/top_level.txt
chromosight-1.6.3.dist-info/RECORD
